feather_creator/__init__.py
feather_creator/create_feather.py
feather_creator/mapping.py
feather_creator/motifsearch.py
feather_creator-0.0.3.dist-info/METADATA
feather_creator-0.0.3.dist-info/WHEEL
feather_creator-0.0.3.dist-info/top_level.txt
feather_creator-0.0.3.dist-info/RECORD
