Metadata-Version: 2.1
Name: feather-creator
Version: 0.0.3
Summary: motif-TG .feather files creation and motifs-TF mapping from a list
Home-page: UNKNOWN
Author: Timothée Frouté and Sergio Peignier
Author-email: sergio.peignier@insa-lyon.fr
License: UNKNOWN
Platform: UNKNOWN
Classifier: Programming Language :: Python :: 3
Classifier: License :: OSI Approved :: GNU General Public License (GPL)
Classifier: Operating System :: OS Independent
Requires-Dist: numpy (==1.19.5)
Requires-Dist: biopython (==1.73)
Requires-Dist: pyarrow (==0.16.0)
Requires-Dist: pandas
Requires-Dist: tqdm
